phitter/__init__.py
phitter/main.py
phitter/continuous/__init__.py
phitter/continuous/phitter_continuous.py
phitter/continuous/continuous_distributions/__init__.py
phitter/continuous/continuous_distributions/alpha.py
phitter/continuous/continuous_distributions/arcsine.py
phitter/continuous/continuous_distributions/argus.py
phitter/continuous/continuous_distributions/beta.py
phitter/continuous/continuous_distributions/beta_prime.py
phitter/continuous/continuous_distributions/beta_prime_4p.py
phitter/continuous/continuous_distributions/bradford.py
phitter/continuous/continuous_distributions/burr.py
phitter/continuous/continuous_distributions/burr_4p.py
phitter/continuous/continuous_distributions/cauchy.py
phitter/continuous/continuous_distributions/chi_square.py
phitter/continuous/continuous_distributions/chi_square_3p.py
phitter/continuous/continuous_distributions/dagum.py
phitter/continuous/continuous_distributions/dagum_4p.py
phitter/continuous/continuous_distributions/erlang.py
phitter/continuous/continuous_distributions/erlang_3p.py
phitter/continuous/continuous_distributions/error_function.py
phitter/continuous/continuous_distributions/exponential.py
phitter/continuous/continuous_distributions/exponential_2p.py
phitter/continuous/continuous_distributions/f.py
phitter/continuous/continuous_distributions/f_4p.py
phitter/continuous/continuous_distributions/fatigue_life.py
phitter/continuous/continuous_distributions/folded_normal.py
phitter/continuous/continuous_distributions/frechet.py
phitter/continuous/continuous_distributions/gamma.py
phitter/continuous/continuous_distributions/gamma_3p.py
phitter/continuous/continuous_distributions/generalized_extreme_value.py
phitter/continuous/continuous_distributions/generalized_gamma.py
phitter/continuous/continuous_distributions/generalized_gamma_4p.py
phitter/continuous/continuous_distributions/generalized_logistic.py
phitter/continuous/continuous_distributions/generalized_normal.py
phitter-1.0.4.dist-info/licenses/LICENSE
phitter-1.0.4.dist-info/METADATA
phitter-1.0.4.dist-info/WHEEL
phitter-1.0.4.dist-info/top_level.txt
phitter-1.0.4.dist-info/RECORD
