Metadata-Version: 2.4
Name: phitter
Version: 1.0.4
Summary: Find the best probability distribution for your dataset and simulate processes and queues
Author-email: Sebastián José Herrera Monterrosa <phitter.email@gmail.com>, Carlos Andrés Másmela Pinilla <phitter.email@gmail.com>
License-Expression: MIT
Project-URL: Homepage, https://phitter.io
Project-URL: Documentation, https://docs-phitter-kernel.netlify.app/
Project-URL: Repository, https://github.com/phitter-hub/phitter-kernel
Keywords: scientific,engineering,mathematics,artificial intelligence,software development,python modules
Classifier: Intended Audience :: Education
Classifier: Intended Audience :: End Users/Desktop
Classifier: Intended Audience :: Developers
Classifier: Intended Audience :: Science/Research
Classifier: Topic :: Scientific/Engineering
Classifier: Topic :: Scientific/Engineering :: Mathematics
Classifier: Topic :: Scientific/Engineering :: Artificial Intelligence
Classifier: Topic :: Software Development
Classifier: Topic :: Software Development :: Libraries
Classifier: Topic :: Software Development :: Libraries :: Python Modules
Classifier: Topic :: Scientific/Engineering :: Bio-Informatics
Classifier: Topic :: Scientific/Engineering :: Information Analysis
Classifier: Programming Language :: Python
Classifier: Programming Language :: Python :: 3 :: Only
Classifier: Programming Language :: Python :: 3.9
Classifier: Programming Language :: Python :: 3.10
Classifier: Programming Language :: Python :: 3.11
Classifier: Programming Language :: Python :: 3.12
Requires-Python: >=3.9
License-File: LICENSE
Requires-Dist: scipy>=1.1.0
Requires-Dist: plotly>=5.14.0
Requires-Dist: kaleido>=0.2.1
Requires-Dist: matplotlib>=3.3
Requires-Dist: pandas>=1.5.0
Requires-Dist: graphviz>=0.5.1
Requires-Dist: IPython>=0.13
Dynamic: license-file
